LICENSE
README.rst
setup.cfg
setup.py
certbot_dns_easydns/__init__.py
certbot_dns_easydns/_version.py
certbot_dns_easydns/dns_easydns.py
certbot_dns_easydns/dns_easydns_test.py
certbot_dns_easydns.egg-info/PKG-INFO
certbot_dns_easydns.egg-info/SOURCES.txt
certbot_dns_easydns.egg-info/dependency_links.txt
certbot_dns_easydns.egg-info/entry_points.txt
certbot_dns_easydns.egg-info/requires.txt
certbot_dns_easydns.egg-info/top_level.txt