Metadata-Version: 2.1
Name: certbot-dns-easydns
Version: 0.1.2
Summary: EasyDNS Authenticator plugin for Certbot
Home-page: https://github.com/easydns/certbot-dns-easydns
Author: Caleb S. Cullen
Author-email: certbot-dev@easydns.com
License: Apache License 2.0
Project-URL: Bug Tracker, https://github.com/easydns/certbot-dns-easydns/issues
Project-URL: Documentation, https://github.com/easydns/certbot-dns-easydns/
Project-URL: Source Code, https://github.com/easydns/certbot-dns-easydns/
Project-URL: Release Notes, https://github.com/easydns/certbot-dns-easydns/blob/main/CHANGELOG.md
Classifier: Development Status :: 3 - Alpha
Classifier: Environment :: Plugins
Classifier: Intended Audience :: System Administrators
Classifier: License :: OSI Approved :: Apache Software License
Classifier: Operating System :: POSIX :: Linux
Classifier: Programming Language :: Python
Classifier: Programming Language :: Python :: 2
Classifier: Programming Language :: Python :: 2.7
Classifier: Programming Language :: Python :: 3
Classifier: Programming Language :: Python :: 3.4
Classifier: Programming Language :: Python :: 3.5
Classifier: Programming Language :: Python :: 3.6
Classifier: Programming Language :: Python :: 3.7
Classifier: Topic :: Internet :: WWW/HTTP
Classifier: Topic :: Security
Classifier: Topic :: System :: Installation/Setup
Classifier: Topic :: System :: Networking
Classifier: Topic :: System :: Systems Administration
Classifier: Topic :: Utilities
Requires-Python: >=2.7, !=3.0.*, !=3.1.*, !=3.2.*, !=3.3.*
Provides-Extra: docs
Provides-Extra: test
License-File: LICENSE
